lti/__init__.py
lti/contentitem_response.py
lti/launch_params.py
lti/outcome_request.py
lti/outcome_response.py
lti/tool_base.py
lti/tool_config.py
lti/tool_consumer.py
lti/tool_outbound.py
lti/tool_provider.py
lti/tool_proxy.py
lti/utils.py
lti/contrib/__init__.py
lti/contrib/django/__init__.py
lti/contrib/django/django_tool_provider.py
lti/contrib/flask/__init__.py
lti/contrib/flask/flask_tool_provider.py
lti-0.9.5.dist-info/AUTHORS.rst
lti-0.9.5.dist-info/LICENSE.rst
lti-0.9.5.dist-info/METADATA
lti-0.9.5.dist-info/WHEEL
lti-0.9.5.dist-info/top_level.txt
lti-0.9.5.dist-info/zip-safe
lti-0.9.5.dist-info/RECORD
