Metadata-Version: 1.2
Name: lti
Version: 0.9.5
Summary: A python library for building and/or consuming LTI apps
Home-page: https://github.com/pylti/lti
Maintainer: Ryan Hiebert
Maintainer-email: ryan@ryanhiebert.com
License: MIT License
Keywords: lti
Platform: UNKNOWN
Classifier: Programming Language :: Python :: 2
Classifier: Programming Language :: Python :: 2.7
Classifier: Programming Language :: Python :: 3
Classifier: Programming Language :: Python :: 3.5
Classifier: Programming Language :: Python :: 3.6
Classifier: Programming Language :: Python :: 3.7
Classifier: Programming Language :: Python :: 3.8
